mi/__init__.py
mi/api.py
mi/bot.py
mi/chart.py
mi/client.py
mi/config.py
mi/conn.py
mi/drive.py
mi/emoji.py
mi/exception.py
mi/http.py
mi/instance.py
mi/note.py
mi/router.py
mi/user.py
mi/utils.py
mi/ext/__init__.py
mi/ext/commands/__init__.py
mi/ext/commands/_types.py
mi/ext/commands/bot.py
mi/ext/commands/cog.py
mi/ext/commands/context.py
mi/ext/commands/core.py
mi/ext/commands/view.py
mi/ext/messages/__init__.py
mi/ext/messages/context.py
mi/ext/task/__init__.py
mi.py-0.2.5.dist-info/COPYING.md
mi.py-0.2.5.dist-info/LICENSE.md
mi.py-0.2.5.dist-info/METADATA
mi.py-0.2.5.dist-info/WHEEL
mi.py-0.2.5.dist-info/top_level.txt
mi.py-0.2.5.dist-info/RECORD
