Metadata-Version: 2.1
Name: mi.py
Version: 0.2.5
Summary: A Python wrapper for the Misskey API
Home-page: https://github.com/yupix/mi.py
Author: yupix
Author-email: yupi0982@outlook.jp
License: MIT
Platform: UNKNOWN
Classifier: Development Status :: 2 - Pre-Alpha
Classifier: Programming Language :: Python :: 3.9
Classifier: Programming Language :: Python :: 3.10
Classifier: Natural Language :: Japanese
Classifier: License :: OSI Approved :: MIT License
Requires-Python: >=3.9, <4.0
License-File: LICENSE.md
License-File: COPYING.md
Requires-Dist: websockets
Requires-Dist: requests
Requires-Dist: pydantic
Requires-Dist: emoji
